shconfparser/__init__.py
shconfparser/exceptions.py
shconfparser/models.py
shconfparser/parser.py
shconfparser/protocols.py
shconfparser/py.typed
shconfparser/reader.py
shconfparser/search.py
shconfparser/shsplit.py
shconfparser/table_parser.py
shconfparser/tree_parser.py
shconfparser/xpath.py
shconfparser-3.1.1.dist-info/METADATA
shconfparser-3.1.1.dist-info/WHEEL
shconfparser-3.1.1.dist-info/licenses/LICENSE
shconfparser-3.1.1.dist-info/RECORD
