Metadata-Version: 2.4
Name: shconfparser
Version: 3.1.1
Summary: Network configuration parser that translates show command outputs into structured data
Project-URL: Homepage, https://github.com/network-tools/shconfparser
Project-URL: Documentation, https://github.com/network-tools/shconfparser#readme
Project-URL: Repository, https://github.com/network-tools/shconfparser
Project-URL: Issues, https://github.com/network-tools/shconfparser/issues
Project-URL: Changelog, https://github.com/network-tools/shconfparser/blob/master/CHANGELOG.md
Author-email: Kiran Kumar Kotari <kirankotari@live.com>
License: MIT
License-File: LICENSE
Keywords: cisco,conf,configuration-management,network,network-automation,output,parser,show,translator
Classifier: Development Status :: 5 - Production/Stable
Classifier: Intended Audience :: Developers
Classifier: Intended Audience :: System Administrators
Classifier: Intended Audience :: Telecommunications Industry
Classifier: License :: OSI Approved :: MIT License
Classifier: Programming Language :: Python :: 3
Classifier: Programming Language :: Python :: 3.9
Classifier: Programming Language :: Python :: 3.10
Classifier: Programming Language :: Python :: 3.11
Classifier: Programming Language :: Python :: 3.12
Classifier: Programming Language :: Python :: 3.13
Classifier: Topic :: Software Development :: Libraries :: Python Modules
Classifier: Topic :: System :: Networking
Classifier: Typing :: Typed
Requires-Python: >=3.9
